mlflow_k8sstore/__init__.py
mlflow_k8sstore/mlflow_k8sstore.py
mlflow_test_plugin-0.0.1.dist-info/METADATA
mlflow_test_plugin-0.0.1.dist-info/WHEEL
mlflow_test_plugin-0.0.1.dist-info/entry_points.txt
mlflow_test_plugin-0.0.1.dist-info/top_level.txt
mlflow_test_plugin-0.0.1.dist-info/RECORD
