Metadata-Version: 2.1
Name: mlflow-test-plugin
Version: 0.0.1
Summary: Test plugin for MLflow
Requires-Dist: mlflow
